{
  "$schema": "https://mintlify.com/schema.json",
  "name": "Starter Kit",
  "logo": {
    "dark": "/logo/white_astrape_vorticity.png",
    "light": "/logo/astrape_vorticity.png"
  },
  "favicon": "/favicon.svg",
  "colors": {
    "primary": "#2980B9",
    "light": "#3498DB",
    "dark": "#A569BD",
    "anchors": {
      "from": "#A569BD",
      "to": "#3498DB"
    }
  },
  "primaryTab": {
    "name": "Overview"
  },
  "topbarLinks": [
    {
      "name": "Support",
      "url": "mailto:astrape@vorticity.xyz"
    }
  ],
  "topbarCtaButton": {
    "name": "Vorticity",
    "url": "https://vorticity.xyz/"
  },
  "tabs": [
    {
      "name": "2.5D AEM",
      "url": "25_aem"
    },
    {
      "name": "3D AEM",
      "url": "3_aem"
    },
    {
      "name": "Configuration Files",
      "url": "configuration"
    },
    {
      "name": "Coming Soon ...",
      "url": "coming_soon"
    }
  ],
  "navigation": [
    {
      "group": "Getting Started",
      "pages": [
        "started/introduction", 
        "started/mission"
      ]
    },
    {
      "group": "Essentials",
      "pages": [
        "essentials/hardware",
        "essentials/ray",
        "essentials/science"
      ]
    },
    {
      "group": "2.5D Airborne Electromagentic Inversions",
      "pages": [
        "25_aem/introduction",        
        "25_aem/workflow"
      ]
    },
    {
      "group": "Running Inversions",
      "pages": [
        "common/step",
        "common/structure",
        "common/data_subfolder"
      ]
    },
    {
      "group": "3D Airborne Electromagentic Inversions",
      "pages": [
        "3_aem/introduction",
        "3_aem/3dworkflow",
              {
      "group": "3D Inversion Outputs",
      "pages": [
        "3_aem/outputs/data",
        "3_aem/outputs/visualization"
      ]
    }
    ]
    },
    {
      "group": "Coming Soon",
      "pages": [
        "coming_soon/mt",
        "coming_soon/requests",
        "coming_soon/uncertainty"
      ]
    },
    {
      "group": "Configuration Files",
      "pages": [
        "configuration/system",
        "configuration/survey",
        "configuration/inversion",
        "configuration/discretization"
      ]
    },
    {
      "group": "2.5D Inversion Outputs",
      "pages": [
        "25_aem/outputs/data",
        "25_aem/outputs/report",
        "25_aem/outputs/visualization",
        "25_aem/outputs/kriging"
      ]
    }
  ],
  "footerSocials": {
    "github": "https://github.com/VORTICITY-INC",
    "linkedin": "https://www.linkedin.com/company/vorticityinc/"
  }
}